esst/__init__.py
esst/__main__.py
esst/_esst_logging.py
esst/config.py
esst/fs_paths.py
esst/atis/__init__.py
esst/atis/_atis_airfields.py
esst/atis/_atis_get_info.py
esst/atis/_atis_identifier.py
esst/atis/_atis_objects.py
esst/atis/_atis_status.py
esst/atis/config.py
esst/atis/create.py
esst/atis/init.py
esst/atis/tts.py
esst/atis/_univers_radio/__init__.py
esst/atis/_univers_radio/_ur_install_dir.py
esst/atis/_univers_radio/_ur_object.py
esst/atis/_univers_radio/_ur_status.py
esst/atis/_univers_radio/_ur_voice_service.py
esst/atis/_univers_radio/_ur_voice_service_settings.py
esst/atis/chat_commands/__init__.py
esst/atis/chat_commands/atis_discord_commands.py
esst/commands/__init__.py
esst/core/__init__.py
esst/core/context.py
esst/core/status.py
esst/dcs/__init__.py
esst/dcs/autoexec_cfg.py
esst/dcs/commands.py
esst/dcs/config.py
esst/dcs/config_server.py
esst/dcs/dcs.py
esst/dcs/dedicated.py
esst/dcs/game_gui.py
esst/dcs/mission_editor_lua.py
esst/dcs/missions_manager.py
esst/dcs/rotate_logs.py
esst/dcs/server_settings.py
esst/dcs/templates/__init__.py
esst/dcs/templates/game_gui.lua
esst/dcs/templates/me_authorization.lua
esst/dcs/templates/settings.lua
esst/discord_bot/__init__.py
esst/discord_bot/abstract.py
esst/discord_bot/catch_exc.py
esst/discord_bot/commands.py
esst/discord_bot/config.py
esst/discord_bot/discord_bot.py
esst/discord_bot/events.py
esst/discord_bot/logging_handler.py
esst/discord_bot/tasks.py
esst/discord_bot/chat_commands/__init__.py
esst/discord_bot/chat_commands/dcs.py
esst/discord_bot/chat_commands/esst_.py
esst/discord_bot/chat_commands/mission.py
esst/discord_bot/chat_commands/parser.py
esst/discord_bot/chat_commands/report.py
esst/discord_bot/chat_commands/server.py
esst/discord_bot/chat_commands/weather.py
esst/listener/__init__.py
esst/listener/commands.py
esst/listener/config.py
esst/listener/listener.py
esst/mission/__init__.py
esst/mission/context.py
esst/mission/state.py
esst/mission/store.py
esst/sentry/__init__.py
esst-2018.12.21.1.dist-info/LICENSE
esst-2018.12.21.1.dist-info/METADATA
esst-2018.12.21.1.dist-info/WHEEL
esst-2018.12.21.1.dist-info/entry_points.txt
esst-2018.12.21.1.dist-info/top_level.txt
esst-2018.12.21.1.dist-info/RECORD
