Metadata-Version: 2.1
Name: esst
Version: 2018.12.21.1
Summary: UNKNOWN
Home-page: UNKNOWN
License: MIT
Platform: UNKNOWN
Classifier: Development Status :: 3 - Alpha
Classifier: Environment :: Win32 (MS Windows)
Classifier: Intended Audience :: End Users/Desktop
Classifier: Natural Language :: English
Classifier: Operating System :: Microsoft :: Windows :: Windows 7
Classifier: Operating System :: Microsoft :: Windows :: Windows 8
Classifier: Operating System :: Microsoft :: Windows :: Windows 8.1
Classifier: Operating System :: Microsoft :: Windows :: Windows 10
Classifier: License :: OSI Approved :: MIT License
Classifier: Programming Language :: Python :: 3.6
Classifier: Programming Language :: Python :: 3.7
Classifier: Topic :: Games/Entertainment :: Simulation
Classifier: Topic :: System :: Systems Administration
Classifier: Topic :: Utilities
Requires-Python: >=3.6
Requires-Dist: attrs
Requires-Dist: argh
Requires-Dist: certifi
Requires-Dist: click
Requires-Dist: configobj
Requires-Dist: discord.py
Requires-Dist: everett
Requires-Dist: humanize
Requires-Dist: jinja2
Requires-Dist: matplotlib
Requires-Dist: metar
Requires-Dist: mpmath
Requires-Dist: natsort
Requires-Dist: numpy
Requires-Dist: pefile
Requires-Dist: psutil
Requires-Dist: python-dateutil
Requires-Dist: pytz
Requires-Dist: pyyaml
Requires-Dist: raven
Requires-Dist: requests
Requires-Dist: urllib3
Requires-Dist: inflect
Requires-Dist: elib-config
Requires-Dist: elib-wx
Requires-Dist: gtts
Provides-Extra: callgraph
Requires-Dist: pycallgraph ; extra == 'callgraph'
